fastauth/__init__.py
fastauth/contrib/__init__.py
fastauth/contrib/sqlalchemy/__init__.py
fastauth/contrib/sqlalchemy/_generic.py
fastauth/contrib/sqlalchemy/models.py
fastauth/contrib/sqlalchemy/repositories.py
fastauth/exceptions.py
fastauth/fastauth.py
fastauth/models/__init__.py
fastauth/models/oauth.py
fastauth/models/rbac.py
fastauth/models/users.py
fastauth/repositories/__init__.py
fastauth/repositories/base.py
fastauth/repositories/oauths.py
fastauth/repositories/roles.py
fastauth/repositories/users.py
fastauth/routes/__init__.py
fastauth/routes/auth.py
fastauth/routes/oauth.py
fastauth/routes/password_reset.py
fastauth/routes/signup.py
fastauth/routes/users.py
fastauth/routes/verification.py
fastauth/schemas/__init__.py
fastauth/schemas/auth.py
fastauth/schemas/base.py
fastauth/schemas/oauth.py
fastauth/schemas/users.py
fastauth/services/__init__.py
fastauth/services/auth.py
fastauth/settings.py
fastauth/storage/__init__.py
fastauth/storage/base.py
fastauth/storage/jwt.py
fastauth/transport/__init__.py
fastauth/transport/base.py
fastauth/transport/bearer.py
fastauth/transport/cookie.py
fastauth/types.py
fastauth/utils/__init__.py
fastauth/utils/jwt_helper.py
fastauth/utils/password.py
fastauth/utils/router.py
fastauth/utils/time.py
fastapi_fastauth-1.1.2.dist-info/LICENSE
fastapi_fastauth-1.1.2.dist-info/METADATA
fastapi_fastauth-1.1.2.dist-info/WHEEL
fastapi_fastauth-1.1.2.dist-info/RECORD
