Metadata-Version: 2.3
Name: fastapi-fastauth
Version: 1.1.2
Summary: Ready-to-use customizable solution for FastAPI with Authentication, Access Controle and OAuth2 support
License: MIT
Keywords: FastAPI,Authentication,Authorization,OAuth2,RBAC,JWTHelper,Cookie,Session
Author: Vladyslav Chaliuk
Author-email: chaliukvladyslav@gmail.com
Requires-Python: >=3.11, <4.0
Classifier: Development Status :: 4 - Beta
Classifier: Programming Language :: Python
Classifier: Programming Language :: Python :: 3.10
Classifier: Programming Language :: Python :: 3.11
Classifier: Programming Language :: Python :: 3.12
Classifier: Programming Language :: Python :: 3.13
Classifier: Framework :: Pydantic :: 2
Classifier: Framework :: FastAPI
Classifier: Topic :: Security
Classifier: Topic :: Internet :: WWW/HTTP :: Session
Provides-Extra: oauth2
Provides-Extra: sqlalchemy
Requires-Dist: fastapi (>=0.115.12,<0.116.0)
Requires-Dist: httpx-oauth (>=0.16.1) ; extra == "oauth2"
Requires-Dist: pwdlib[argon2,bcrypt] (>=0.2.1,<0.3.0)
Requires-Dist: pydantic-settings (>=2.9.1,<3.0.0)
Requires-Dist: pydantic[email] (>=2.11.5,<3.0.0)
Requires-Dist: pyjwt (>=2.10.1,<3.0.0)
Requires-Dist: python-multipart (>=0.0.20,<0.0.21)
Requires-Dist: sqlalchemy (>=2.0.41) ; extra == "sqlalchemy"
Project-URL: Documentation, https://astralmortem.github.io/fastapi-fastauth/
Project-URL: Source, https://github.com/AstralMortem/fastapi-fastauth
